od2/CONFIG.py
od2/__init__.py
od2/_reestruturar/classe.py
od2/_reestruturar/equipamento.py
od2/_reestruturar/personagem.py
od2/_reestruturar/raca.py
od2/data/__init__.py
od2/data/atributos.py
od2/data/dados_api.py
od2/data/filtros.py
od2/data/modificadores.py
od2/data/tesouros.py
od2/data/api/__init__.py
od2/data/api/campanhas.py
od2/data/api/classes.py
od2/data/api/equipamentos.py
od2/data/api/livros.py
od2/data/api/magias.py
od2/data/api/monstros.py
od2/data/api/personagens.py
od2/data/api/racas.py
od2/entidade/__init__.py
od2/entidade/entidade.py
od2/entidade/monstro.py
od2/helpers/__init__.py
od2/helpers/atributo.py
od2/helpers/converter_tipo.py
od2/helpers/moedas.py
od2/helpers/retorna_atributo.py
od2/helpers/rolagens.py
od2/utils/__init__.py
od2/utils/gera_atributos.py
od2/utils/gera_renda_inicial.py
od2/utils/tesouro_aleatorio.py
od2aag-1.0.1.dist-info/LICENSE
od2aag-1.0.1.dist-info/METADATA
od2aag-1.0.1.dist-info/WHEEL
od2aag-1.0.1.dist-info/top_level.txt
od2aag-1.0.1.dist-info/RECORD
