Metadata-Version: 2.1
Name: od2aag
Version: 1.0.1
Summary: Módulo para Old Dragon 2
Author: Alessandro Guarita
License: MIT
Keywords: old dragon,rpg,od2
Classifier: Programming Language :: Python :: 3
Classifier: License :: OSI Approved :: MIT License
Classifier: Operating System :: OS Independent
Requires-Python: >=3.13
License-File: LICENSE
Requires-Dist: TTRPGaag
